pygcd/__init__.py
pygcd/__version__.py
pygcd/dataset.py
pygcd/drivers/__init__.py
pygcd/drivers/_cells.py
pygcd/drivers/_utils.py
pygcd/drivers/geopandas_driver.py
pygcd/drivers/lasio_driver.py
pygcd/drivers/pyvista_driver.py
pygcd/objects/__init__.py
pygcd/objects/abstract.py
pygcd/objects/grid.py
pygcd/objects/mesh.py
pygcd/objects/well.py
pygcd/readers/__init__.py
pygcd/readers/_utils.py
pygcd/readers/grid.py
pygcd/readers/header.py
pygcd/readers/mesh.py
pygcd/readers/well.py
pygcd-0.3.1.post1.dist-info/licenses/LICENSE
pygcd-0.3.1.post1.dist-info/METADATA
pygcd-0.3.1.post1.dist-info/WHEEL
pygcd-0.3.1.post1.dist-info/top_level.txt
pygcd-0.3.1.post1.dist-info/RECORD
