Metadata-Version: 2.4
Name: pygcd
Version: 0.3.1.post1
Summary: A simple python module to parse GOCAD ASCII exports
Author: BRGM
Maintainer-email: Thomas JANVIER <t.janvier@brgm.fr>
License:                     GNU AFFERO GENERAL PUBLIC LICENSE
Project-URL: homepage, https://gitlab.brgm.fr/brgm/geomodelling/io/pygcd
Project-URL: repository, https://gitlab.brgm.fr/brgm/geomodelling/io/pygcd
Classifier: Programming Language :: Python :: 3
Classifier: License :: OSI Approved :: GNU Affero General Public License v3 or later (AGPLv3+)
Classifier: Topic :: Scientific/Engineering
Requires-Python: >=3
License-File: LICENSE
Requires-Dist: numpy
Requires-Dist: scipy
Provides-Extra: test
Requires-Dist: pytest; extra == "test"
Provides-Extra: drivers
Requires-Dist: pyvista; extra == "drivers"
Requires-Dist: geopandas; extra == "drivers"
Requires-Dist: lasio; extra == "drivers"
Dynamic: license-file
